{"pageProps":{"post":{"slug":"bash-guide","id":"66e02c5a4d1d260001ae644c","uuid":"bd27c860-d877-42da-a34e-7d920454bb58","title":"Bash Guide","html":null,"comment_id":"66d903f5fb4c95071862daa7","feature_image":"http://localhost:2368/content/images/2024/09/4.png","featured":false,"visibility":"public","created_at":"2024-09-05T01:05:57.000+00:00","updated_at":"2024-09-05T14:19:36.000+00:00","published_at":"2024-09-05T01:09:43.000+00:00","custom_excerpt":null,"codeinjection_head":"<script type=\"application/json\">\n  { \n  \"guide_name\":\"bash-guide\",\n  \"guide_display_name\":\"Bash Guide\",\n  \"guide_description\":\"Learn how to find keywords that your audience searches for in Google, YouTube and other popular search engines.\",\n  \"priority\": 0\n  }\n</script>","codeinjection_foot":null,"custom_template":null,"canonical_url":null,"url":"http://localhost:2368/bash-guide/","excerpt":null,"access":true,"comments":false,"og_image":null,"og_title":null,"og_description":null,"twitter_image":null,"twitter_title":null,"twitter_description":null,"meta_title":null,"meta_description":null,"email_subject":null,"frontmatter":null,"feature_image_alt":null,"feature_image_caption":null},"previous":{"id":"66e02c5a4d1d260001ae644b","uuid":"ee70d7af-92da-4565-90c1-56a547279739","title":"Linux Guide","slug":"linux-guide","html":null,"comment_id":"66d8fc66fb4c95071862da92","feature_image":"http://localhost:2368/content/images/2024/09/linux.png","featured":false,"visibility":"public","created_at":"2024-09-05T00:33:42.000+00:00","updated_at":"2024-09-05T01:36:51.000+00:00","published_at":"2024-09-05T00:37:38.000+00:00","custom_excerpt":null,"codeinjection_head":"<script type=\"application/json\">\n  { \n  \"guide_name\":\"linux-guide\",\n  \"guide_display_name\":\"Linux Guide\",\n  \"guide_description\":\"Learn how to find keywords that your audience searches for in Google, YouTube and other popular search engines.\",\n  \"priority\": 0\n  }\n</script>","codeinjection_foot":null,"custom_template":null,"canonical_url":null,"tags":[{"id":"66e02c594d1d260001ae642e","name":"#Import 2024-09-10 11:24","slug":"hash-import-2024-09-10-11-24","description":null,"feature_image":null,"visibility":"internal","og_image":null,"og_title":null,"og_description":null,"twitter_image":null,"twitter_title":null,"twitter_description":null,"meta_title":null,"meta_description":null,"codeinjection_head":null,"codeinjection_foot":null,"canonical_url":null,"accent_color":null,"url":"http://localhost:2368/404/"}],"primary_tag":null,"url":"http://localhost:2368/linux-guide/","excerpt":null,"access":true,"comments":false,"og_image":null,"og_title":null,"og_description":null,"twitter_image":null,"twitter_title":null,"twitter_description":null,"meta_title":null,"meta_description":null,"email_subject":null,"frontmatter":null,"feature_image_alt":null,"feature_image_caption":null},"next":{"id":"66e02c5a4d1d260001ae644d","uuid":"e817fbdc-9f36-4e4d-83f6-dbc07a75b6ce","title":"DevOps Guide","slug":"devops-guide","html":null,"comment_id":"66d9bd8e85e60507c6e2f3ef","feature_image":"http://localhost:2368/content/images/2024/09/1.png","featured":false,"visibility":"public","created_at":"2024-09-05T14:17:50.000+00:00","updated_at":"2024-09-05T14:19:40.000+00:00","published_at":"2024-09-05T14:18:44.000+00:00","custom_excerpt":null,"codeinjection_head":"<script type=\"application/json\">\n  { \n  \"guide_name\":\"devops-guide\",\n  \"guide_display_name\":\"DevOps Guide\",\n  \"guide_description\":\"Learn how to find keywords that your audience searches for in Google, YouTube and other popular search engines.\",\n  \"priority\": 0\n  }\n</script>","codeinjection_foot":null,"custom_template":null,"canonical_url":null,"tags":[{"id":"66e02c594d1d260001ae642e","name":"#Import 2024-09-10 11:24","slug":"hash-import-2024-09-10-11-24","description":null,"feature_image":null,"visibility":"internal","og_image":null,"og_title":null,"og_description":null,"twitter_image":null,"twitter_title":null,"twitter_description":null,"meta_title":null,"meta_description":null,"codeinjection_head":null,"codeinjection_foot":null,"canonical_url":null,"accent_color":null,"url":"http://localhost:2368/404/"}],"primary_tag":null,"url":"http://localhost:2368/devops-guide/","excerpt":null,"access":true,"comments":false,"og_image":null,"og_title":null,"og_description":null,"twitter_image":null,"twitter_title":null,"twitter_description":null,"meta_title":null,"meta_description":null,"email_subject":null,"frontmatter":null,"feature_image_alt":null,"feature_image_caption":null}},"__N_SSG":true}